DNAFMIndex/__init__.py
DNAFMIndex/_dna_fm_index.py
DNAFMIndex/_dna_fm_index_ctypes.py
DNAFMIndex/lib/libawfmindex.so
DNAFMIndex/lib/libdivsufsort64.so
DNAFMIndex/lib/libdivsufsort64.so.3
DNAFMIndex/lib/libdivsufsort64.so.3.0.1
DNAFMIndex/lib/libfastavector.so
dnafmindex-0.1.0.dist-info/licenses/LICENSE
dnafmindex-0.1.0.dist-info/METADATA
dnafmindex-0.1.0.dist-info/WHEEL
dnafmindex-0.1.0.dist-info/top_level.txt
dnafmindex-0.1.0.dist-info/RECORD
