Metadata-Version: 2.4
Name: DNAFMIndex
Version: 0.1.0
Summary: Python wrapper for AvxWindowFmIndex library
Author-email: mehelborn <mr.4uldum@gmail.com>, tocl19 <ael.mak1504@gmail.com>
License: BSD 3-Clause License
Project-URL: Homepage, https://github.com/Mehelborn/DNAFMIndex
Project-URL: Repository, https://github.com/Mehelborn/DNAFMIndex
Requires-Python: >=3.8
License-File: LICENSE
Dynamic: license-file
